[
 {
  "artifactid": "codegen",
  "groupid": "com.mysema.codegen",
  "version": "0.1.0",
  "package": "jar",
  "scope": null,
  "omitted": false,
  "omitted_reason": null,
  "child": [
   {
    "artifactid": "collections-generic",
    "groupid": "net.sourceforge.collections",
    "version": "4.01",
    "package": "jar",
    "scope": "compile",
    "omitted": false,
    "omitted_reason": null,
    "child": []
   },
   {
    "artifactid": "mysema-commons-lang",
    "groupid": "com.mysema.commons",
    "version": "0.1.7",
    "package": "jar",
    "scope": "compile",
    "omitted": false,
    "omitted_reason": null,
    "child": [
     {
      "artifactid": "slf4j-api",
      "groupid": "org.slf4j",
      "version": "1.5.2",
      "package": "jar",
      "scope": "compile",
      "omitted": false,
      "omitted_reason": null,
      "child": []
     }
    ]
   },
   {
    "artifactid": "commons-lang",
    "groupid": "commons-lang",
    "version": "2.4",
    "package": "jar",
    "scope": "compile",
    "omitted": false,
    "omitted_reason": null,
    "child": []
   },
   {
    "artifactid": "junit",
    "groupid": "junit",
    "version": "4.4",
    "package": "jar",
    "scope": "test",
    "omitted": false,
    "omitted_reason": null,
    "child": []
   }
  ]
 }
]